anysearch.py
anysearch-0.1.3.dist-info/LICENSE
anysearch-0.1.3.dist-info/METADATA
anysearch-0.1.3.dist-info/WHEEL
anysearch-0.1.3.dist-info/top_level.txt
anysearch-0.1.3.dist-info/RECORD
