Metadata-Version: 2.1
Name: anysearch
Version: 0.1.3
Summary: Elasticsearch and OpenSearch compatibility library.
Home-page: https://github.com/barseghyanartur/anysearch/
Author: Artur Barseghyan
Author-email: artur.barseghyan@gmail.com
License: MIT
Project-URL: Bug Tracker, https://github.com/barseghyanartur/anysearch/issues
Project-URL: Documentation, https://anysearch.readthedocs.io/
Project-URL: Source Code, https://github.com/barseghyanartur/anysearch/
Project-URL: Changelog, https://anysearch.readthedocs.io/en/latest/changelog.html
Keywords: django,elasticsearch,elasticsearch-dsl,opensearch,opensearch-dsl
Classifier: Programming Language :: Python :: 3.7
Classifier: Programming Language :: Python :: 3.8
Classifier: Programming Language :: Python :: 3.9
Classifier: Programming Language :: Python :: 3.10
Classifier: Environment :: Web Environment
Classifier: License :: OSI Approved :: MIT License
Classifier: Topic :: Internet :: WWW/HTTP :: Indexing/Search
Classifier: Intended Audience :: Developers
Classifier: Operating System :: OS Independent
Classifier: Development Status :: 4 - Beta
Requires-Python: >=3.7
License-File: LICENSE
